main.py
pythonterrier-0.0.1.dist-info/LICENCE
pythonterrier-0.0.1.dist-info/METADATA
pythonterrier-0.0.1.dist-info/WHEEL
pythonterrier-0.0.1.dist-info/top_level.txt
pythonterrier-0.0.1.dist-info/RECORD
