Metadata-Version: 2.1
Name: pythonterrier
Version: 0.0.1
Summary: Terrier IR Python API
Home-page: https://github.com/A-Tsolov/Pyterrier
Author: A-Tsolov
Author-email: tsolov.aleksandar@gmail.com
License: UNKNOWN
Platform: UNKNOWN
Classifier: Programming Language :: Python :: 3
Classifier: License :: OSI Approved :: MIT License
Classifier: Operating System :: OS Independent
Requires-Python: >=3.6
